mapillary_downloader/__init__.py
mapillary_downloader/__main__.py
mapillary_downloader/client.py
mapillary_downloader/downloader.py
mapillary_downloader/exif_writer.py
mapillary_downloader/ia_check.py
mapillary_downloader/ia_meta.py
mapillary_downloader/ia_stats.py
mapillary_downloader/logging_config.py
mapillary_downloader/metadata_reader.py
mapillary_downloader/tar_sequences.py
mapillary_downloader/utils.py
mapillary_downloader/webp_converter.py
mapillary_downloader/worker.py
mapillary_downloader/worker_pool.py
mapillary_downloader/xmp_writer.py
mapillary_downloader-0.8.0.dist-info/entry_points.txt
mapillary_downloader-0.8.0.dist-info/licenses/LICENSE.md
mapillary_downloader-0.8.0.dist-info/WHEEL
mapillary_downloader-0.8.0.dist-info/METADATA
mapillary_downloader-0.8.0.dist-info/RECORD
