Metadata-Version: 2.4
Name: mapillary_downloader
Version: 0.8.0
Summary: Archive user data from Mapillary
Author-email: Gareth Davidson <gaz@bitplane.net>
Requires-Python: >=3.10
Classifier: License :: Public Domain
Classifier: Programming Language :: Python :: 3
Classifier: Programming Language :: Python :: 3.10
Classifier: Programming Language :: Python :: 3.11
Classifier: Programming Language :: Python :: 3.12
License-File: LICENSE.md
Requires-Dist: requests>=2.31.0
Requires-Dist: piexif>=1.1.3
Requires-Dist: pre-commit ; extra == "dev"
Requires-Dist: pytest ; extra == "dev"
Requires-Dist: coverage ; extra == "dev"
Requires-Dist: pytest-cov ; extra == "dev"
Requires-Dist: build ; extra == "dev"
Requires-Dist: twine ; extra == "dev"
Requires-Dist: ruff ; extra == "dev"
Requires-Dist: pydoc-markdown ; extra == "dev"
Requires-Dist: Pillow ; extra == "dev"
Project-URL: Documentation, https://bitplane.net/dev/python/mapillary_downloader/pydoc
Project-URL: Homepage, https://bitplane.net/dev/python/mapillary_downloader
Project-URL: Issues, https://github.com/bitplane/mapillary_downloader/issues
Project-URL: Repository, https://github.com/bitplane/mapillary_downloader
Provides-Extra: dev
